pyMikroTik/__init__.py
pyMikroTik/exceptions.py
pyMikroTik/interface.py
pyMikroTik/ip.py
pyMikroTik/ppp.py
pyMikroTik/pymikrotik.py
pyMikroTik/router_objects.py
pyMikroTik/utilites.py
pyMikroTik-0.1.5.dist-info/METADATA
pyMikroTik-0.1.5.dist-info/WHEEL
pyMikroTik-0.1.5.dist-info/top_level.txt
pyMikroTik-0.1.5.dist-info/RECORD
